setup.py
Client/__init__.py
Client/client.py
Client/client/__init__.py
Client/client/transport.py
Client/client/database/__init__.py
Client/client/database/client_database.py
Client/client/interface/__init__.py
Client/client/interface/add_contact.py
Client/client/interface/del_contact.py
Client/client/interface/main_window.py
Client/client/interface/main_window_conv.py
Client/client/interface/start_dialog.py
Client/common/__init__.py
Client/common/const.py
Client/common/decor.py
Client/common/descriptors.py
Client/common/errors.py
Client/common/metaclasses.py
Client/common/utils.py
Client/logs/__init__.py
Client/logs/client_log_config.py
Client/logs/server_log_config.py
Client/tests/__init__.py
Client/tests/test_client.py
Client/tests/test_server.py
Client/tests/test_utils.py
my_chat_client_nov.egg-info/PKG-INFO
my_chat_client_nov.egg-info/SOURCES.txt
my_chat_client_nov.egg-info/dependency_links.txt
my_chat_client_nov.egg-info/requires.txt
my_chat_client_nov.egg-info/top_level.txt