Metadata-Version: 1.0
Name: my-chat-client-nov
Version: 1.0.0
Summary: my_chat_client
Home-page: UNKNOWN
Author: Kopylov Dmitry
Author-email: kopylovdk@gmail.com
License: UNKNOWN
Platform: UNKNOWN
